<lircmap>
 
<remote device="digital">
 
  <left>KEY_LEFT</left>
  <right>KEY_RIGHT</right>
  <up>KEY_UP</up>
  <down>KEY_DOWN</down>
  <select>KEY_OK</select>
  <back>KEY_BACK</back>
 
  <play>KEY_PLAY</play>
  <pause>KEY_PAUSE</pause>
  <stop>KEY_STOP</stop>
 
  <volumeplus>KEY_VOLUMEUP</volumeplus>
  <volumeminus>KEY_VOLUMEDOWN</volumeminus>
  <mute>KEY_MUTE</mute>
 
  <pageplus>KEY_PAGEUP</pageplus>
  <pageminus>KEY_PAGEDOWN</pageminus>
 
  <power>KEY_POWER</power>
  <menu>KEY_MENU</menu>
  <info>KEY_INFO</info>
  <display>KEY_DISPLAYTOGGLE</display>
  <title>KEY_TITLE</title>
 
  <red>KEY_RED</red>
  <green>KEY_GREEN</green>
  <yellow>KEY_YELLOW</yellow>
  <blue>KEY_BLUE</blue>
 
  <zero>KEY_0</zero>
  <one>KEY_1</one>
  <two>KEY_2</two>
  <three>KEY_3</three>
  <four>KEY_4</four>
  <five>KEY_5</five>
  <six>KEY_6</six>
  <seven>KEY_7</seven>
  <eight>KEY_8</eight>
  <nine>KEY_9</nine>
 
  <skipplus></skipplus>
  <skipminus></skipminus>
 
  <reverse></reverse>
  <forward></forward>
 
  <subtitle>KEY_SUBTITLE</subtitle>
  <language></language>
 
  <channelplus></channelplus>
  <channelminus></channelminus>
 
  <mytv></mytv>
  <mymusic></mymusic>
  <mypictures></mypictures>
  <myvideo>KEY_VIDEO</myvideo>
  <livetv></livetv>
  <recordedtv></recordedtv>
  <liveradio></liveradio>
  <epgsearch></epgsearch>
 
  <guide></guide>
 
  <record></record>
  <start></start>
 
  <star></star>
  <hash></hash>
  <clear></clear>
  <enter></enter>
 
  <playlist></playlist>
 
  </remote>
 
</lircmap>
